bingomatic/__init__.py
bingomatic/_version.py
bingomatic/cli.py
bingomatic/config.py
bingomatic/pdf.py
bingomatic/fonts/Roboto-Bold.ttf
bingomatic/fonts/Roboto-Regular.ttf
bingomatic/fonts/RobotoMono-Regular.ttf
bingomatic-1.2.0.dist-info/METADATA
bingomatic-1.2.0.dist-info/WHEEL
bingomatic-1.2.0.dist-info/entry_points.txt
bingomatic-1.2.0.dist-info/licenses/LICENSE
bingomatic-1.2.0.dist-info/RECORD
