Metadata-Version: 2.4
Name: bingomatic
Version: 1.2.0
Summary: A bingo card generator for conferences like DevOpsDays
Project-URL: Homepage, https://github.com/richardboydii/bingomatic
Project-URL: Repository, https://github.com/richardboydii/bingomatic
Project-URL: Documentation, https://github.com/richardboydii/bingomatic#readme
Author-email: Richard Boyd II <registration@richardboydii.com>
Maintainer-email: Richard Boyd II <registration@richardboydii.com>
License: Apache-2.0
License-File: LICENSE
Keywords: bingo,cli,conference,devopsdays,pdf
Classifier: Environment :: Console
Classifier: Intended Audience :: End Users/Desktop
Classifier: License :: OSI Approved :: Apache Software License
Classifier: Operating System :: OS Independent
Classifier: Programming Language :: Python :: 3
Classifier: Programming Language :: Python :: 3.12
Classifier: Programming Language :: Python :: 3.13
Classifier: Topic :: Utilities
Requires-Python: >=3.12
Requires-Dist: click>=8.0
Requires-Dist: pyyaml>=6.0
Requires-Dist: reportlab>=4.0
